{"name": "Best Man", "type": "relic", "img": "https://global-uploads.webflow.com/5ff36780a1084987868ce198/6265280223fd21b1bc1aadae_Championship%20Ring%20(WL).png", "system": {"description": "+25 Max Shields.", "effect": "+25 Max Shields.", "level": 1, "special": {"overrideType": ""}, "isLoot": true, "quantity": 1, "cost": 500, "guild": "", "rarity": {"name": "Rare", "value": "rare", "colorValue": "#00a0ff"}, "carried": true, "equipped": false, "redText": "", "redTextEffect": "", "redTextEffectBM": "", "class": "Psycho", "classEffect": "+20 Recharge Rate."}, "effects": [], "flags": {"exportSource": {"world": "bnb-testing", "system": "bunkers-and-badasses", "coreVersion": "10.286", "systemVersion": "0.3.5"}}, "_stats": {"systemId": "bunkers-and-badasses", "systemVersion": "0.3.5", "coreVersion": "10.286", "createdTime": 1670192505015, "modifiedTime": 1670192505015, "lastModifiedBy": "EbqGN0VlirtxVP9W"}}